hgext3rd/fastimport/__init__.py
hgext3rd/fastimport/hgechoprocessor.py
hgext3rd/fastimport/hgimport.py
hgext3rd/fastimport/vendor/python_fastimport/__init__.py
hgext3rd/fastimport/vendor/python_fastimport/commands.py
hgext3rd/fastimport/vendor/python_fastimport/dates.py
hgext3rd/fastimport/vendor/python_fastimport/errors.py
hgext3rd/fastimport/vendor/python_fastimport/helpers.py
hgext3rd/fastimport/vendor/python_fastimport/parser.py
hgext3rd/fastimport/vendor/python_fastimport/processor.py
hgext3rd/fastimport/vendor/python_fastimport/reftracker.py
hg_fastimport-0.1.1.dist-info/COPYING
hg_fastimport-0.1.1.dist-info/METADATA
hg_fastimport-0.1.1.dist-info/WHEEL
hg_fastimport-0.1.1.dist-info/top_level.txt
hg_fastimport-0.1.1.dist-info/RECORD
