Metadata-Version: 2.1
Name: hg-fastimport
Version: 0.1.1
Summary: Mercurial extension for importing a git fast-import stream.
Home-page: https://roy.marples.name/hg/hg-fastimport/
Author: The hg-fastimport authors
Maintainer: Roy Marples
Maintainer-email: roy@marples.name
License: GPLv2
Keywords: hg git mercurial
Platform: UNKNOWN
Requires-Python: >=2.7, !=3.0.*, !=3.1.*, !=3.2.*, !=3.3.*, !=3.4.*, !=3.5.*, <4
